{
  "version": 3,
  "middleware": {
    "/": {
      "files": [
        "server/edge-runtime-webpack.js",
        "server/middleware.js"
      ],
      "name": "middleware",
      "page": "/",
      "matchers": [
        {
          "regexp": "^(?:\\/(_next\\/data\\/[^/]{1,}))?(?:\\/((?!_next\\/static|_next\\/image|favicon.ico).*))(\\.json)?[\\/#\\?]?$",
          "originalSource": "/((?!_next/static|_next/image|favicon.ico).*)"
        }
      ],
      "wasm": [],
      "assets": [],
      "env": {
        "__NEXT_BUILD_ID": "z12WywjNIcGmp30lASOiA",
        "NEXT_SERVER_ACTIONS_ENCRYPTION_KEY": "MuFe3cQZTjA/F9tIReC4lnvnt4p6h5T8O8MuT73IiuE=",
        "__NEXT_PREVIEW_MODE_ID": "623b0c4d150f0c5d802cf4309ed7cbae",
        "__NEXT_PREVIEW_MODE_ENCRYPTION_KEY": "5d40c471eb7c777ad5e943e416b95be59858f322eb647f34d260ce34576a042c",
        "__NEXT_PREVIEW_MODE_SIGNING_KEY": "333d81c92e21601b933499380750ef0a44b143ffdfbb0e7a9243b2b62abc574c"
      }
    }
  },
  "functions": {},
  "sortedMiddleware": [
    "/"
  ]
}