{
  "version": 3,
  "middleware": {
    "/": {
      "files": [
        "server/edge-runtime-webpack.js",
        "server/middleware.js"
      ],
      "name": "middleware",
      "page": "/",
      "matchers": [
        {
          "regexp": "^(?:\\/(_next\\/data\\/[^/]{1,}))?(?:\\/((?!_next\\/static|_next\\/image|favicon.ico).*))(.json)?[\\/#\\?]?$",
          "originalSource": "/((?!_next/static|_next/image|favicon.ico).*)"
        }
      ],
      "wasm": [],
      "assets": [],
      "env": {
        "__NEXT_BUILD_ID": "xPCrZcGaXAI2GUg2X96nb",
        "NEXT_SERVER_ACTIONS_ENCRYPTION_KEY": "WPsW3uEYq66DkmQYvwl14n5kjEY2RhwbBORLNxEsZ3Y=",
        "__NEXT_PREVIEW_MODE_ID": "22b8619a66e59a2f0e4c4b00ca4c406b",
        "__NEXT_PREVIEW_MODE_ENCRYPTION_KEY": "77477435bd4fb14566a6f0f607aec89af0031d58654906eddea2156be6dd3541",
        "__NEXT_PREVIEW_MODE_SIGNING_KEY": "3204a48dde14a54aa542a7ba3c6944901ca53b962041814ca2b27935cdbd68a3"
      }
    }
  },
  "functions": {},
  "sortedMiddleware": [
    "/"
  ]
}